hblab/__init__.py
hblab/lab.py
hblab-1.0.2.dist-info/LICENSE
hblab-1.0.2.dist-info/METADATA
hblab-1.0.2.dist-info/WHEEL
hblab-1.0.2.dist-info/top_level.txt
hblab-1.0.2.dist-info/RECORD
