Metadata-Version: 2.1
Name: hblab
Version: 1.0.2
Summary: AIML LAB
Home-page: https://github.com/pypa/sampleproject
Author: hypebalaga
Author-email: hypebalaga@gmail.com
Project-URL: Bug Tracker, https://github.com/pypa/sampleproject/issues
Classifier: Programming Language :: Python :: 3
Classifier: License :: OSI Approved :: MIT License
Classifier: Operating System :: OS Independent
Requires-Python: >=3.6
License-File: LICENSE
